<xml xmlns="http://www.w3.org/1999/xhtml"><block type="procedures_defnoreturn" id="}#Kb!Jlw4F)4j3uL(B2q" x="-951" y="-104"><field name="NAME">effect5</field><comment pinned="false" h="80" w="160">描述该功能...</comment><statement name="STACK"><block type="hc_show_picture_n" id="mvw1x-7n5Z?7]ih5h*b}"><value name="picture"><shadow type="picture14" id="CTtzsZ~xcA`KYeB[Ko~x"><field name="picture">#333333-#333333-#333333-#333333-#333333-#333333-#333333-#333333-#333333-#333333-#333333-#333333-#333333-#333333-#333333-#333333-#333333-#333333-#333333-#333333-#333333-#333333-#333333-#333333-#333333-#333333-#333333-#ffff00-#00ff00-#333333-#333333-#333333-#333333-#333333-#333333-#00ffff-#ffffff-#333333-#333333-#333333-#333333-#333333-#333333-#333333-#333333-#333333-#333333-#333333-#333333-#333333-#333333-#333333-#333333-#333333-#333333-#333333-#333333-#333333-#333333-#333333-#333333-#333333-#333333-#333333-#333333-#333333-#333333-#333333-#333333-#333333-#333333-#333333-#333333-#333333-#333333-#333333-#333333-#333333-#333333-#333333-#333333-#333333-#333333-#333333-#333333-#333333-#333333-#333333-#333333-#333333-#333333-#ffffff-#ffff00-#333333-#333333-#333333-#333333-#333333-#333333-#00ff00-#ff0000-#333333-#333333-#333333-#333333-#333333-#333333-#333333-#333333-#333333-#333333-#333333-#333333-#333333-#333333-#333333-#333333-#333333-#333333-#333333-#333333-#333333-#333333-#333333-#333333-#333333-#333333-#333333</field></shadow></value><next><block type="time_delay" id="CU/w!WO3_0-1~h+-LgsH"><value name="DELAY_TIME_MILI"><block type="math_number" id="@8Bd6wv^Rveo8)6R39_i"><field name="NUM">50</field></block></value><next><block type="hc_show_picture_n" id="]!(7}kz4yu+:%^ahPSpp"><value name="picture"><shadow type="picture14" id="?(KSPkTo|(Rw1`0}M3/_"><field name="picture">#333333-#333333-#333333-#333333-#333333-#333333-#333333-#333333-#333333-#333333-#333333-#333333-#333333-#333333-#333333-#333333-#333333-#333333-#333333-#ffff00-#00ff00-#333333-#333333-#333333-#333333-#333333-#ffff00-#ffff00-#00ff00-#00ff00-#333333-#333333-#333333-#333333-#00ffff-#00ffff-#ffffff-#ffffff-#333333-#333333-#333333-#333333-#333333-#00ffff-#ffffff-#333333-#333333-#333333-#333333-#333333-#333333-#333333-#333333-#333333-#333333-#333333-#333333-#333333-#333333-#333333-#333333-#333333-#333333-#333333-#333333-#333333-#333333-#333333-#333333-#333333-#333333-#333333-#333333-#333333-#333333-#333333-#333333-#333333-#333333-#333333-#333333-#333333-#333333-#ffffff-#ffff00-#333333-#333333-#333333-#333333-#333333-#ffffff-#ffffff-#ffff00-#ffff00-#333333-#333333-#333333-#333333-#00ff00-#00ff00-#ff0000-#ff0000-#333333-#333333-#333333-#333333-#333333-#00ff00-#ff0000-#333333-#333333-#333333-#333333-#333333-#333333-#333333-#333333-#333333-#333333-#333333-#333333-#333333-#333333-#333333-#333333-#333333-#333333-#333333</field></shadow></value><next><block type="time_delay" id="ot:r;cw6;^(ax};M}0L-"><value name="DELAY_TIME_MILI"><block type="math_number" id="ofraumgwN4b-^G38?I,v"><field name="NUM">50</field></block></value><next><block type="hc_show_picture_n" id="a~t==LV0H4r{Uwy%IP,g"><value name="picture"><shadow type="picture14" id="hBI`q@LKFa|ba{!|ts2;"><field name="picture">#333333-#333333-#333333-#333333-#333333-#333333-#333333-#333333-#333333-#333333-#333333-#ffff00-#00ff00-#333333-#333333-#333333-#333333-#333333-#ffff00-#ffff00-#00ff00-#00ff00-#333333-#333333-#333333-#ffff00-#ffff00-#ffff00-#00ff00-#00ff00-#00ff00-#333333-#333333-#00ffff-#00ffff-#00ffff-#ffffff-#ffffff-#ffffff-#333333-#333333-#333333-#00ffff-#00ffff-#ffffff-#ffffff-#333333-#333333-#333333-#333333-#333333-#00ffff-#ffffff-#333333-#333333-#333333-#333333-#333333-#333333-#333333-#333333-#333333-#333333-#333333-#333333-#333333-#333333-#333333-#333333-#333333-#333333-#333333-#333333-#333333-#333333-#ffffff-#ffff00-#333333-#333333-#333333-#333333-#333333-#ffffff-#ffffff-#ffff00-#ffff00-#333333-#333333-#333333-#ffffff-#ffffff-#ffffff-#ffff00-#ffff00-#ffff00-#333333-#333333-#00ff00-#00ff00-#00ff00-#ff0000-#ff0000-#ff0000-#333333-#333333-#333333-#00ff00-#00ff00-#ff0000-#ff0000-#333333-#333333-#333333-#333333-#333333-#00ff00-#ff0000-#333333-#333333-#333333-#333333-#333333-#333333-#333333-#333333-#333333-#333333-#333333</field></shadow></value><next><block type="time_delay" id="Weo{Egrga+}+-}]sp4@A"><value name="DELAY_TIME_MILI"><block type="math_number" id="u,r@7(nCeisW7|Aae%O0"><field name="NUM">50</field></block></value><next><block type="hc_show_picture_n" id=":{1~^g8iKUTOWX6@X^[M"><value name="picture"><shadow type="picture14" id="q:@d*Ufb;7UkZodC3?Q}"><field name="picture">#333333-#333333-#333333-#ffff00-#00ff00-#333333-#333333-#333333-#333333-#333333-#ffff00-#ffff00-#00ff00-#00ff00-#333333-#333333-#333333-#ffff00-#ffff00-#ffff00-#00ff00-#00ff00-#00ff00-#333333-#ffff00-#ffff00-#ffff00-#ffff00-#00ff00-#00ff00-#00ff00-#00ff00-#00ffff-#00ffff-#00ffff-#00ffff-#ffffff-#ffffff-#ffffff-#ffffff-#333333-#00ffff-#00ffff-#00ffff-#ffffff-#ffffff-#ffffff-#333333-#333333-#333333-#00ffff-#00ffff-#ffffff-#ffffff-#333333-#333333-#333333-#333333-#333333-#00ffff-#ffffff-#333333-#333333-#333333-#333333-#333333-#333333-#ffffff-#ffff00-#333333-#333333-#333333-#333333-#333333-#ffffff-#ffffff-#ffff00-#ffff00-#333333-#333333-#333333-#ffffff-#ffffff-#ffffff-#ffff00-#ffff00-#ffff00-#333333-#ffffff-#ffffff-#ffffff-#ffffff-#ffff00-#ffff00-#ffff00-#ffff00-#00ff00-#00ff00-#00ff00-#00ff00-#ff0000-#ff0000-#ff0000-#ff0000-#333333-#00ff00-#00ff00-#00ff00-#ff0000-#ff0000-#ff0000-#333333-#333333-#333333-#00ff00-#00ff00-#ff0000-#ff0000-#333333-#333333-#333333-#333333-#333333-#00ff00-#ff0000-#333333-#333333-#333333</field></shadow></value><next><block type="time_delay" id="@,%@*4!y.]XSwfP?H:}Z"><value name="DELAY_TIME_MILI"><block type="math_number" id="7V[I%z[tV32:0nUXmCUa"><field name="NUM">50</field></block></value><next><block type="hc_show_picture_n" id="@f3r%MGY6=Op-)})|*My"><value name="picture"><shadow type="picture14" id="0p2Poa)YOKN)^,:DZdQA"><field name="picture">#333333-#333333-#ffff00-#ffff00-#00ff00-#00ff00-#333333-#333333-#333333-#ffff00-#ffff00-#ffff00-#00ff00-#00ff00-#00ff00-#333333-#ffff00-#ffff00-#ffff00-#ffff00-#00ff00-#00ff00-#00ff00-#00ff00-#ffff00-#ffff00-#ffff00-#ffff00-#00ff00-#00ff00-#00ff00-#00ff00-#00ffff-#00ffff-#00ffff-#00ffff-#ffffff-#ffffff-#ffffff-#ffffff-#00ffff-#00ffff-#00ffff-#00ffff-#ffffff-#ffffff-#ffffff-#ffffff-#333333-#00ffff-#00ffff-#00ffff-#ffffff-#ffffff-#ffffff-#333333-#333333-#333333-#00ffff-#00ffff-#ffffff-#ffffff-#333333-#333333-#333333-#333333-#ffffff-#ffffff-#ffff00-#ffff00-#333333-#333333-#333333-#ffffff-#ffffff-#ffffff-#ffff00-#ffff00-#ffff00-#333333-#ffffff-#ffffff-#ffffff-#ffffff-#ffff00-#ffff00-#ffff00-#ffff00-#ffffff-#ffffff-#ffffff-#ffffff-#ffff00-#ffff00-#ffff00-#ffff00-#00ff00-#00ff00-#00ff00-#00ff00-#ff0000-#ff0000-#ff0000-#ff0000-#00ff00-#00ff00-#00ff00-#00ff00-#ff0000-#ff0000-#ff0000-#ff0000-#333333-#00ff00-#00ff00-#00ff00-#ff0000-#ff0000-#ff0000-#333333-#333333-#333333-#00ff00-#00ff00-#ff0000-#ff0000-#333333-#333333</field></shadow></value><next><block type="time_delay" id="fx`*=kBIoI5muBkr5v5d"><value name="DELAY_TIME_MILI"><block type="math_number" id="WdHog,r[3dgiE=UZ=*.R"><field name="NUM">50</field></block></value><next><block type="hc_show_picture_n" id=")=4|`6#x`jmayubJG[up"><value name="picture"><shadow type="picture14" id="V~9#c]FR`_6Fm_8BQ,i="><field name="picture">#333333-#ffff00-#ffff00-#ffff00-#00ff00-#00ff00-#00ff00-#333333-#ffff00-#ffff00-#ffff00-#ffff00-#00ff00-#00ff00-#00ff00-#00ff00-#ffff00-#ffff00-#ffff00-#ffff00-#00ff00-#00ff00-#00ff00-#00ff00-#ffff00-#ffff00-#ffff00-#ffff00-#00ff00-#00ff00-#00ff00-#00ff00-#00ffff-#00ffff-#00ffff-#00ffff-#ffffff-#ffffff-#ffffff-#ffffff-#00ffff-#00ffff-#00ffff-#00ffff-#ffffff-#ffffff-#ffffff-#ffffff-#00ffff-#00ffff-#00ffff-#00ffff-#ffffff-#ffffff-#ffffff-#ffffff-#333333-#00ffff-#00ffff-#00ffff-#ffffff-#ffffff-#ffffff-#333333-#333333-#ffffff-#ffffff-#ffffff-#ffff00-#ffff00-#ffff00-#333333-#ffffff-#ffffff-#ffffff-#ffffff-#ffff00-#ffff00-#ffff00-#ffff00-#ffffff-#ffffff-#ffffff-#ffffff-#ffff00-#ffff00-#ffff00-#ffff00-#ffffff-#ffffff-#ffffff-#ffffff-#ffff00-#ffff00-#ffff00-#ffff00-#00ff00-#00ff00-#00ff00-#00ff00-#ff0000-#ff0000-#ff0000-#ff0000-#00ff00-#00ff00-#00ff00-#00ff00-#ff0000-#ff0000-#ff0000-#ff0000-#00ff00-#00ff00-#00ff00-#00ff00-#ff0000-#ff0000-#ff0000-#ff0000-#333333-#00ff00-#00ff00-#00ff00-#ff0000-#ff0000-#ff0000-#333333</field></shadow></value><next><block type="time_delay" id="KyU9b^_(rHBcb;zITuTL"><value name="DELAY_TIME_MILI"><block type="math_number" id="vCC`f,oyjJuYS^YUAKsW"><field name="NUM">50</field></block></value><next><block type="hc_show_picture_n" id="([bvM9G!L.To5Ii!ewIh"><value name="picture"><shadow type="picture14" id="Qr0(GMYy5D{%jN.Iw:e="><field name="picture">#333333-#ffff00-#ffff00-#ffff00-#00ff00-#00ff00-#00ff00-#333333-#ffff00-#ffff00-#ffff00-#ffff00-#00ff00-#00ff00-#00ff00-#00ff00-#ffff00-#ffff00-#ffff00-#ffff00-#00ff00-#00ff00-#00ff00-#00ff00-#ffff00-#ffff00-#ffff00-#ffff00-#00ff00-#00ff00-#00ff00-#00ff00-#00ffff-#00ffff-#00ffff-#00ffff-#ffffff-#ffffff-#ffffff-#ffffff-#00ffff-#00ffff-#00ffff-#00ffff-#ffffff-#ffffff-#ffffff-#ffffff-#00ffff-#00ffff-#00ffff-#00ffff-#ffffff-#ffffff-#ffffff-#ffffff-#333333-#00ffff-#00ffff-#00ffff-#ffffff-#ffffff-#ffffff-#333333-#333333-#ffffff-#ffffff-#ffffff-#ffff00-#ffff00-#ffff00-#333333-#ffffff-#ffffff-#ffffff-#ffffff-#ffff00-#ffff00-#ffff00-#ffff00-#ffffff-#ffffff-#ffffff-#ffffff-#ffff00-#ffff00-#ffff00-#ffff00-#ffffff-#ffffff-#ffffff-#ffffff-#ffff00-#ffff00-#ffff00-#ffff00-#00ff00-#00ff00-#00ff00-#00ff00-#ff0000-#ff0000-#ff0000-#ff0000-#00ff00-#00ff00-#00ff00-#00ff00-#ff0000-#ff0000-#ff0000-#ff0000-#00ff00-#00ff00-#00ff00-#00ff00-#ff0000-#ff0000-#ff0000-#ff0000-#333333-#00ff00-#00ff00-#00ff00-#ff0000-#ff0000-#ff0000-#333333</field></shadow></value><next><block type="procedures_callnoreturn" id="~JwvS3tTJ-L~O]n9Enr%"><mutation name="effect4"></mutation><next><block type="procedures_callnoreturn" id="@gv+a7wKW#`vlDMz[N6H"><mutation name="effect4"></mutation><next><block type="time_delay" id="7aIqg#4TgwhGYR5S3A8,"><value name="DELAY_TIME_MILI"><block type="math_number" id="2b5@Rd0xi0fZxs+/hkbv"><field name="NUM">50</field></block></value><next><block type="hc_show_picture_n" id="`NlW1p,Q]si#h0H/o^C)"><value name="picture"><shadow type="picture14" id="5tD_`]}GcRcg%GF_Zvd]"><field name="picture">#333333-#333333-#ffff00-#ffff00-#00ff00-#00ff00-#333333-#333333-#333333-#ffff00-#ffff00-#ffff00-#00ff00-#00ff00-#00ff00-#333333-#ffff00-#ffff00-#ffff00-#ffff00-#00ff00-#00ff00-#00ff00-#00ff00-#ffff00-#ffff00-#ffff00-#ffff00-#00ff00-#00ff00-#00ff00-#00ff00-#00ffff-#00ffff-#00ffff-#00ffff-#ffffff-#ffffff-#ffffff-#ffffff-#00ffff-#00ffff-#00ffff-#00ffff-#ffffff-#ffffff-#ffffff-#ffffff-#333333-#00ffff-#00ffff-#00ffff-#ffffff-#ffffff-#ffffff-#333333-#333333-#333333-#00ffff-#00ffff-#ffffff-#ffffff-#333333-#333333-#333333-#333333-#ffffff-#ffffff-#ffff00-#ffff00-#333333-#333333-#333333-#ffffff-#ffffff-#ffffff-#ffff00-#ffff00-#ffff00-#333333-#ffffff-#ffffff-#ffffff-#ffffff-#ffff00-#ffff00-#ffff00-#ffff00-#ffffff-#ffffff-#ffffff-#ffffff-#ffff00-#ffff00-#ffff00-#ffff00-#00ff00-#00ff00-#00ff00-#00ff00-#ff0000-#ff0000-#ff0000-#ff0000-#00ff00-#00ff00-#00ff00-#00ff00-#ff0000-#ff0000-#ff0000-#ff0000-#333333-#00ff00-#00ff00-#00ff00-#ff0000-#ff0000-#ff0000-#333333-#333333-#333333-#00ff00-#00ff00-#ff0000-#ff0000-#333333-#333333</field></shadow></value><next><block type="time_delay" id="FW#GeKjc1-1bt[01bfy5"><value name="DELAY_TIME_MILI"><block type="math_number" id="t)b^z%]GrDnwSHE?Qr9#"><field name="NUM">50</field></block></value><next><block type="hc_show_picture_n" id="%Z(}PdZQ)_9Vw_ewPlgT"><value name="picture"><shadow type="picture14" id="4GK:fzJV@})((|4tCdiH"><field name="picture">#333333-#333333-#333333-#ffff00-#00ff00-#333333-#333333-#333333-#333333-#333333-#ffff00-#ffff00-#00ff00-#00ff00-#333333-#333333-#333333-#ffff00-#ffff00-#ffff00-#00ff00-#00ff00-#00ff00-#333333-#ffff00-#ffff00-#ffff00-#ffff00-#00ff00-#00ff00-#00ff00-#00ff00-#00ffff-#00ffff-#00ffff-#00ffff-#ffffff-#ffffff-#ffffff-#ffffff-#333333-#00ffff-#00ffff-#00ffff-#ffffff-#ffffff-#ffffff-#333333-#333333-#333333-#00ffff-#00ffff-#ffffff-#ffffff-#333333-#333333-#333333-#333333-#333333-#00ffff-#ffffff-#333333-#333333-#333333-#333333-#333333-#333333-#ffffff-#ffff00-#333333-#333333-#333333-#333333-#333333-#ffffff-#ffffff-#ffff00-#ffff00-#333333-#333333-#333333-#ffffff-#ffffff-#ffffff-#ffff00-#ffff00-#ffff00-#333333-#ffffff-#ffffff-#ffffff-#ffffff-#ffff00-#ffff00-#ffff00-#ffff00-#00ff00-#00ff00-#00ff00-#00ff00-#ff0000-#ff0000-#ff0000-#ff0000-#333333-#00ff00-#00ff00-#00ff00-#ff0000-#ff0000-#ff0000-#333333-#333333-#333333-#00ff00-#00ff00-#ff0000-#ff0000-#333333-#333333-#333333-#333333-#333333-#00ff00-#ff0000-#333333-#333333-#333333</field></shadow></value><next><block type="time_delay" id="/d*zF%aG2dnEN+Xo1OHq"><value name="DELAY_TIME_MILI"><block type="math_number" id="ZbO7H%j^8)w;Z|!R9atx"><field name="NUM">50</field></block></value><next><block type="hc_show_picture_n" id="1I8`e/[@zE3V]~RY`3Bo"><value name="picture"><shadow type="picture14" id=":Vp~jj^M#n6%LctVpe_J"><field name="picture">#333333-#333333-#333333-#333333-#333333-#333333-#333333-#333333-#333333-#333333-#333333-#ffff00-#00ff00-#333333-#333333-#333333-#333333-#333333-#ffff00-#ffff00-#00ff00-#00ff00-#333333-#333333-#333333-#ffff00-#ffff00-#ffff00-#00ff00-#00ff00-#00ff00-#333333-#333333-#00ffff-#00ffff-#00ffff-#ffffff-#ffffff-#ffffff-#333333-#333333-#333333-#00ffff-#00ffff-#ffffff-#ffffff-#333333-#333333-#333333-#333333-#333333-#00ffff-#ffffff-#333333-#333333-#333333-#333333-#333333-#333333-#333333-#333333-#333333-#333333-#333333-#333333-#333333-#333333-#333333-#333333-#333333-#333333-#333333-#333333-#333333-#333333-#ffffff-#ffff00-#333333-#333333-#333333-#333333-#333333-#ffffff-#ffffff-#ffff00-#ffff00-#333333-#333333-#333333-#ffffff-#ffffff-#ffffff-#ffff00-#ffff00-#ffff00-#333333-#333333-#00ff00-#00ff00-#00ff00-#ff0000-#ff0000-#ff0000-#333333-#333333-#333333-#00ff00-#00ff00-#ff0000-#ff0000-#333333-#333333-#333333-#333333-#333333-#00ff00-#ff0000-#333333-#333333-#333333-#333333-#333333-#333333-#333333-#333333-#333333-#333333-#333333</field></shadow></value><next><block type="time_delay" id="XHk`5thkmn/Ox?-o|mhq"><value name="DELAY_TIME_MILI"><block type="math_number" id="x[ZT#}NULftD0bs)8Iw_"><field name="NUM">50</field></block></value><next><block type="hc_show_picture_n" id="?a;Q?-_()A`g07c,Q-}v"><value name="picture"><shadow type="picture14" id="_]aJ|l.N8!oq4,@Mh`@A"><field name="picture">#333333-#333333-#333333-#333333-#333333-#333333-#333333-#333333-#333333-#333333-#333333-#333333-#333333-#333333-#333333-#333333-#333333-#333333-#333333-#ffff00-#00ff00-#333333-#333333-#333333-#333333-#333333-#ffff00-#ffff00-#00ff00-#00ff00-#333333-#333333-#333333-#333333-#00ffff-#00ffff-#ffffff-#ffffff-#333333-#333333-#333333-#333333-#333333-#00ffff-#ffffff-#333333-#333333-#333333-#333333-#333333-#333333-#333333-#333333-#333333-#333333-#333333-#333333-#333333-#333333-#333333-#333333-#333333-#333333-#333333-#333333-#333333-#333333-#333333-#333333-#333333-#333333-#333333-#333333-#333333-#333333-#333333-#333333-#333333-#333333-#333333-#333333-#333333-#333333-#ffffff-#ffff00-#333333-#333333-#333333-#333333-#333333-#ffffff-#ffffff-#ffff00-#ffff00-#333333-#333333-#333333-#333333-#00ff00-#00ff00-#ff0000-#ff0000-#333333-#333333-#333333-#333333-#333333-#00ff00-#ff0000-#333333-#333333-#333333-#333333-#333333-#333333-#333333-#333333-#333333-#333333-#333333-#333333-#333333-#333333-#333333-#333333-#333333-#333333-#333333</field></shadow></value><next><block type="time_delay" id="(I!|JmJ]j.ssUg.kmozJ"><value name="DELAY_TIME_MILI"><block type="math_number" id=",vXauqApBi)xzVEYw(%`"><field name="NUM">50</field></block></value><next><block type="hc_show_picture_n" id=".IQhM]wwj3E}zEgkR!0["><value name="picture"><shadow type="picture14" id=".@z/4qX.?hU*u2;=n-P^"><field name="picture">#333333-#333333-#333333-#333333-#333333-#333333-#333333-#333333-#333333-#333333-#333333-#333333-#333333-#333333-#333333-#333333-#333333-#333333-#333333-#333333-#333333-#333333-#333333-#333333-#333333-#333333-#333333-#ffff00-#00ff00-#333333-#333333-#333333-#333333-#333333-#333333-#00ffff-#ffffff-#333333-#333333-#333333-#333333-#333333-#333333-#333333-#333333-#333333-#333333-#333333-#333333-#333333-#333333-#333333-#333333-#333333-#333333-#333333-#333333-#333333-#333333-#333333-#333333-#333333-#333333-#333333-#333333-#333333-#333333-#333333-#333333-#333333-#333333-#333333-#333333-#333333-#333333-#333333-#333333-#333333-#333333-#333333-#333333-#333333-#333333-#333333-#333333-#333333-#333333-#333333-#333333-#333333-#333333-#ffffff-#ffff00-#333333-#333333-#333333-#333333-#333333-#333333-#00ff00-#ff0000-#333333-#333333-#333333-#333333-#333333-#333333-#333333-#333333-#333333-#333333-#333333-#333333-#333333-#333333-#333333-#333333-#333333-#333333-#333333-#333333-#333333-#333333-#333333-#333333-#333333-#333333-#333333</field></shadow></value><next><block type="time_delay" id="Dov{6n!PLzh;d1Yz2F47"><value name="DELAY_TIME_MILI"><block type="math_number" id=",?~JEYW8|y@i=L:*02l;"><field name="NUM">50</field></block></value><next><block type="hc_show_picture_n" id=":Wm/vMXgRvaO2qlP@0p}"><value name="picture"><shadow type="picture14" id="sUKMqoLZ=hx{3}D-JyN`"><field name="picture">#333333-#333333-#333333-#333333-#333333-#333333-#333333-#333333-#333333-#333333-#333333-#333333-#333333-#333333-#333333-#333333-#333333-#333333-#333333-#333333-#333333-#333333-#333333-#333333-#333333-#333333-#333333-#333333-#333333-#333333-#333333-#333333-#333333-#333333-#333333-#333333-#333333-#333333-#333333-#333333-#333333-#333333-#333333-#333333-#333333-#333333-#333333-#333333-#333333-#333333-#333333-#333333-#333333-#333333-#333333-#333333-#333333-#333333-#333333-#333333-#333333-#333333-#333333-#333333-#333333-#333333-#333333-#333333-#333333-#333333-#333333-#333333-#333333-#333333-#333333-#333333-#333333-#333333-#333333-#333333-#333333-#333333-#333333-#333333-#333333-#333333-#333333-#333333-#333333-#333333-#333333-#333333-#333333-#333333-#333333-#333333-#333333-#333333-#333333-#333333-#333333-#333333-#333333-#333333-#333333-#333333-#333333-#333333-#333333-#333333-#333333-#333333-#333333-#333333-#333333-#333333-#333333-#333333-#333333-#333333-#333333-#333333-#333333-#333333-#333333-#333333-#333333-#333333</field></shadow></value><next><block type="time_delay" id="@KS_x?E=3s=%WNg*SFYI"><value name="DELAY_TIME_MILI"><block type="math_number" id="J@aP+#Ki(wwejq=`k4WV"><field name="NUM">100</field></block></value></block></next></block></next></block></next></block></next></block></next></block></next></block></next></block></next></block></next></block></next></block></next></block></next></block></next></block></next></block></next></block></next></block></next></block></next></block></next></block></next></block></next></block></next></block></next></block></next></block></next></block></next></block></next></block></statement></block><block type="procedures_defnoreturn" id="T|xUz/m!:Tgq3,{z;w^j" x="-535" y="-73"><field name="NAME">effect4</field><comment pinned="false" h="80" w="160">描述该功能...</comment><statement name="STACK"><block type="hc_show_picture_n" id="wC^L^^@C5Oe^blKbzRmx"><value name="picture"><shadow type="picture14" id="{QDAeq`UIvDN=O6KkCg,"><field name="picture">#333333-#333333-#ffff00-#ffff00-#00ff00-#00ff00-#333333-#333333-#333333-#ffff00-#ffff00-#ffff00-#00ff00-#00ff00-#00ff00-#333333-#ffff00-#ffff00-#ffff00-#ffff00-#00ff00-#00ff00-#00ff00-#00ff00-#ffff00-#ffff00-#ffff00-#ffff00-#00ff00-#00ff00-#00ff00-#00ff00-#00ffff-#00ffff-#00ffff-#00ffff-#ffffff-#ffffff-#ffffff-#ffffff-#00ffff-#00ffff-#00ffff-#00ffff-#ffffff-#ffffff-#ffffff-#ffffff-#333333-#00ffff-#00ffff-#00ffff-#ffffff-#ffffff-#ffffff-#333333-#333333-#333333-#00ffff-#00ffff-#ffffff-#ffffff-#333333-#333333-#333333-#333333-#ffffff-#ffffff-#ffff00-#ffff00-#333333-#333333-#333333-#ffffff-#ffffff-#ffffff-#ffff00-#ffff00-#ffff00-#333333-#ffffff-#ffffff-#ffffff-#ffffff-#ffff00-#ffff00-#ffff00-#ffff00-#ffffff-#ffffff-#ffffff-#ffffff-#ffff00-#ffff00-#ffff00-#ffff00-#00ff00-#00ff00-#00ff00-#00ff00-#ff0000-#ff0000-#ff0000-#ff0000-#00ff00-#00ff00-#00ff00-#00ff00-#ff0000-#ff0000-#ff0000-#ff0000-#333333-#00ff00-#00ff00-#00ff00-#ff0000-#ff0000-#ff0000-#333333-#333333-#333333-#00ff00-#00ff00-#ff0000-#ff0000-#333333-#333333</field></shadow></value><next><block type="time_delay" id="?bM_T?BgDqR{]~Y]aMY@"><value name="DELAY_TIME_MILI"><block type="math_number" id="oSuhl]+z~)T/(APj)n{2"><field name="NUM">100</field></block></value><next><block type="hc_show_picture_n" id=".y)SX,b5L2qnyad:M8!["><value name="picture"><shadow type="picture14" id="#4TmRmtVsx.rU/#(LRpq"><field name="picture">#333333-#333333-#00ff00-#00ff00-#ffffff-#ffffff-#333333-#333333-#333333-#00ff00-#00ff00-#00ff00-#ffffff-#ffffff-#ffffff-#333333-#00ff00-#00ff00-#00ff00-#00ff00-#ffffff-#ffffff-#ffffff-#ffffff-#00ff00-#00ff00-#00ff00-#00ff00-#ffffff-#ffffff-#ffffff-#ffffff-#ffff00-#ffff00-#ffff00-#ffff00-#00ffff-#00ffff-#00ffff-#00ffff-#ffff00-#ffff00-#ffff00-#ffff00-#00ffff-#00ffff-#00ffff-#00ffff-#333333-#ffff00-#ffff00-#ffff00-#00ffff-#00ffff-#00ffff-#333333-#333333-#333333-#ffff00-#ffff00-#00ffff-#00ffff-#333333-#333333-#333333-#333333-#ffff00-#ffff00-#ff0000-#ff0000-#333333-#333333-#333333-#ffff00-#ffff00-#ffff00-#ff0000-#ff0000-#ff0000-#333333-#ffff00-#ffff00-#ffff00-#ffff00-#ff0000-#ff0000-#ff0000-#ff0000-#ffff00-#ffff00-#ffff00-#ffff00-#ff0000-#ff0000-#ff0000-#ff0000-#ffffff-#ffffff-#ffffff-#ffffff-#00ff00-#00ff00-#00ff00-#00ff00-#ffffff-#ffffff-#ffffff-#ffffff-#00ff00-#00ff00-#00ff00-#00ff00-#333333-#ffffff-#ffffff-#ffffff-#00ff00-#00ff00-#00ff00-#333333-#333333-#333333-#ffffff-#ffffff-#00ff00-#00ff00-#333333-#333333</field></shadow></value><next><block type="time_delay" id="bFrc_ep@rt?J]l6M?Pbp"><value name="DELAY_TIME_MILI"><block type="math_number" id="b|T[mD^JL(4b-%M/{)-*"><field name="NUM">100</field></block></value><next><block type="hc_show_picture_n" id="5fPJ8`rRY1gE+7,ZuQ]6"><value name="picture"><shadow type="picture14" id="S+!8fdQ49=In=UKv:ITL"><field name="picture">#333333-#333333-#ffffff-#ffffff-#ffff00-#ffff00-#333333-#333333-#333333-#ffffff-#ffffff-#ffffff-#ffff00-#ffff00-#ffff00-#333333-#ffffff-#ffffff-#ffffff-#ffffff-#ffff00-#ffff00-#ffff00-#ffff00-#ffffff-#ffffff-#ffffff-#ffffff-#ffff00-#ffff00-#ffff00-#ffff00-#00ff00-#00ff00-#00ff00-#00ff00-#ffff00-#ffff00-#ffff00-#ffff00-#00ff00-#00ff00-#00ff00-#00ff00-#ffff00-#ffff00-#ffff00-#ffff00-#333333-#00ff00-#00ff00-#00ff00-#ffff00-#ffff00-#ffff00-#333333-#333333-#333333-#00ff00-#00ff00-#ffff00-#ffff00-#333333-#333333-#333333-#333333-#ff0000-#ff0000-#00ff00-#00ff00-#333333-#333333-#333333-#ff0000-#ff0000-#ff0000-#00ff00-#00ff00-#00ff00-#333333-#ff0000-#ff0000-#ff0000-#ff0000-#00ff00-#00ff00-#00ff00-#00ff00-#ff0000-#ff0000-#ff0000-#ff0000-#00ff00-#00ff00-#00ff00-#00ff00-#00ffff-#00ffff-#00ffff-#00ffff-#ffffff-#ffffff-#ffffff-#ffffff-#00ffff-#00ffff-#00ffff-#00ffff-#ffffff-#ffffff-#ffffff-#ffffff-#333333-#00ffff-#00ffff-#00ffff-#ffffff-#ffffff-#ffffff-#333333-#333333-#333333-#00ffff-#00ffff-#ffffff-#ffffff-#333333-#333333</field></shadow></value><next><block type="time_delay" id="6,Lk)HreMivF[@2KWe#b"><value name="DELAY_TIME_MILI"><block type="math_number" id="`G[P%^stVNDqecnX^v_!"><field name="NUM">100</field></block></value><next><block type="hc_show_picture_n" id="`DbEwC.e]LLQFkM.iIn%"><value name="picture"><shadow type="picture14" id="k6wVcNHP%K-xZ~j+?w,W"><field name="picture">#333333-#333333-#ffff00-#ffff00-#ff0000-#ff0000-#333333-#333333-#333333-#ffff00-#ffff00-#ffff00-#ff0000-#ff0000-#ff0000-#333333-#ffff00-#ffff00-#ffff00-#ffff00-#ff0000-#ff0000-#ff0000-#ff0000-#ffff00-#ffff00-#ffff00-#ffff00-#ff0000-#ff0000-#ff0000-#ff0000-#ffffff-#ffffff-#ffffff-#ffffff-#00ff00-#00ff00-#00ff00-#00ff00-#ffffff-#ffffff-#ffffff-#ffffff-#00ff00-#00ff00-#00ff00-#00ff00-#333333-#ffffff-#ffffff-#ffffff-#00ff00-#00ff00-#00ff00-#333333-#333333-#333333-#ffffff-#ffffff-#00ff00-#00ff00-#333333-#333333-#333333-#333333-#00ff00-#00ff00-#ffffff-#ffffff-#333333-#333333-#333333-#00ff00-#00ff00-#00ff00-#ffffff-#ffffff-#ffffff-#333333-#00ff00-#00ff00-#00ff00-#00ff00-#ffffff-#ffffff-#ffffff-#ffffff-#00ff00-#00ff00-#00ff00-#00ff00-#ffffff-#ffffff-#ffffff-#ffffff-#ffff00-#ffff00-#ffff00-#ffff00-#00ffff-#00ffff-#00ffff-#00ffff-#ffff00-#ffff00-#ffff00-#ffff00-#00ffff-#00ffff-#00ffff-#00ffff-#333333-#ffff00-#ffff00-#ffff00-#00ffff-#00ffff-#00ffff-#333333-#333333-#333333-#ffff00-#ffff00-#00ffff-#00ffff-#333333-#333333</field></shadow></value><next><block type="time_delay" id="/ZKu2lZ*9IeGU?):x}wy"><value name="DELAY_TIME_MILI"><block type="math_number" id="DWKO|-1}8cz7=M}[vCYn"><field name="NUM">100</field></block></value><next><block type="hc_show_picture_n" id="*oJeYw=m`@a*`O|=axz|"><value name="picture"><shadow type="picture14" id="9yDsr(V-8]JLwIw=U^)2"><field name="picture">#333333-#333333-#ff0000-#ff0000-#00ff00-#00ff00-#333333-#333333-#333333-#ff0000-#ff0000-#ff0000-#00ff00-#00ff00-#00ff00-#333333-#ff0000-#ff0000-#ff0000-#ff0000-#00ff00-#00ff00-#00ff00-#00ff00-#ff0000-#ff0000-#ff0000-#ff0000-#00ff00-#00ff00-#00ff00-#00ff00-#ffff00-#ffff00-#ffff00-#ffff00-#ffffff-#ffffff-#ffffff-#ffffff-#ffff00-#ffff00-#ffff00-#ffff00-#ffffff-#ffffff-#ffffff-#ffffff-#333333-#ffff00-#ffff00-#ffff00-#ffffff-#ffffff-#ffffff-#333333-#333333-#333333-#ffff00-#ffff00-#ffffff-#ffffff-#333333-#333333-#333333-#333333-#ffffff-#ffffff-#00ffff-#00ffff-#333333-#333333-#333333-#ffffff-#ffffff-#ffffff-#00ffff-#00ffff-#00ffff-#333333-#ffffff-#ffffff-#ffffff-#ffffff-#00ffff-#00ffff-#00ffff-#00ffff-#ffffff-#ffffff-#ffffff-#ffffff-#00ffff-#00ffff-#00ffff-#00ffff-#00ff00-#00ff00-#00ff00-#00ff00-#ffff00-#ffff00-#ffff00-#ffff00-#00ff00-#00ff00-#00ff00-#00ff00-#ffff00-#ffff00-#ffff00-#ffff00-#333333-#00ff00-#00ff00-#00ff00-#ffff00-#ffff00-#ffff00-#333333-#333333-#333333-#00ff00-#00ff00-#ffff00-#ffff00-#333333-#333333</field></shadow></value><next><block type="time_delay" id="j!ociA9iPbZbl-tQ9x[6"><value name="DELAY_TIME_MILI"><block type="math_number" id="`|rL0^i7VRLJ-@RIR.YG"><field name="NUM">100</field></block></value><next><block type="hc_show_picture_n" id="4(RzKb|q/{x|%S3*c_8T"><value name="picture"><shadow type="picture14" id=":0.SfzbmRUNz-@G(o.Cn"><field name="picture">#333333-#333333-#00ff00-#00ff00-#ffffff-#ffffff-#333333-#333333-#333333-#00ff00-#00ff00-#00ff00-#ffffff-#ffffff-#ffffff-#333333-#00ff00-#00ff00-#00ff00-#00ff00-#ffffff-#ffffff-#ffffff-#ffffff-#00ff00-#00ff00-#00ff00-#00ff00-#ffffff-#ffffff-#ffffff-#ffffff-#ff0000-#ff0000-#ff0000-#ff0000-#ffff00-#ffff00-#ffff00-#ffff00-#ff0000-#ff0000-#ff0000-#ff0000-#ffff00-#ffff00-#ffff00-#ffff00-#333333-#ff0000-#ff0000-#ff0000-#ffff00-#ffff00-#ffff00-#333333-#333333-#333333-#ff0000-#ff0000-#ffff00-#ffff00-#333333-#333333-#333333-#333333-#00ffff-#00ffff-#ffff00-#ffff00-#333333-#333333-#333333-#00ffff-#00ffff-#00ffff-#ffff00-#ffff00-#ffff00-#333333-#00ffff-#00ffff-#00ffff-#00ffff-#ffff00-#ffff00-#ffff00-#ffff00-#00ffff-#00ffff-#00ffff-#00ffff-#ffff00-#ffff00-#ffff00-#ffff00-#ffffff-#ffffff-#ffffff-#ffffff-#00ff00-#00ff00-#00ff00-#00ff00-#ffffff-#ffffff-#ffffff-#ffffff-#00ff00-#00ff00-#00ff00-#00ff00-#333333-#ffffff-#ffffff-#ffffff-#00ff00-#00ff00-#00ff00-#333333-#333333-#333333-#ffffff-#ffffff-#00ff00-#00ff00-#333333-#333333</field></shadow></value><next><block type="time_delay" id="4C*M{~,h_Q%K8gWpY-j%"><value name="DELAY_TIME_MILI"><block type="math_number" id="[+M-Y]i{9xLtPL:Gt2bR"><field name="NUM">100</field></block></value><next><block type="hc_show_picture_n" id="o.998Ac!~;@4TD!o2S^K"><value name="picture"><shadow type="picture14" id="v|iRRa_em@@O;~dkmS1w"><field name="picture">#333333-#333333-#ffffff-#ffffff-#00ffff-#00ffff-#333333-#333333-#333333-#ffffff-#ffffff-#ffffff-#00ffff-#00ffff-#00ffff-#333333-#ffffff-#ffffff-#ffffff-#ffffff-#00ffff-#00ffff-#00ffff-#00ffff-#ffffff-#ffffff-#ffffff-#ffffff-#00ffff-#00ffff-#00ffff-#00ffff-#00ff00-#00ff00-#00ff00-#00ff00-#ff0000-#ff0000-#ff0000-#ff0000-#00ff00-#00ff00-#00ff00-#00ff00-#ff0000-#ff0000-#ff0000-#ff0000-#333333-#00ff00-#00ff00-#00ff00-#ff0000-#ff0000-#ff0000-#333333-#333333-#333333-#00ff00-#00ff00-#ff0000-#ff0000-#333333-#333333-#333333-#333333-#ffff00-#ffff00-#00ff00-#00ff00-#333333-#333333-#333333-#ffff00-#ffff00-#ffff00-#00ff00-#00ff00-#00ff00-#333333-#ffff00-#ffff00-#ffff00-#ffff00-#00ff00-#00ff00-#00ff00-#00ff00-#ffff00-#ffff00-#ffff00-#ffff00-#00ff00-#00ff00-#00ff00-#00ff00-#ffff00-#ffff00-#ffff00-#ffff00-#ffffff-#ffffff-#ffffff-#ffffff-#ffff00-#ffff00-#ffff00-#ffff00-#ffffff-#ffffff-#ffffff-#ffffff-#333333-#ffff00-#ffff00-#ffff00-#ffffff-#ffffff-#ffffff-#333333-#333333-#333333-#ffff00-#ffff00-#ffffff-#ffffff-#333333-#333333</field></shadow></value><next><block type="time_delay" id="nf,(#j59gN1O50AG48Xs"><value name="DELAY_TIME_MILI"><block type="math_number" id="up/NZtP6|^UYNwgBI)_I"><field name="NUM">100</field></block></value><next><block type="hc_show_picture_n" id="Et_P(;zH-zxd^6#K%0R["><value name="picture"><shadow type="picture14" id="s2{^jMXE@n|(hD;n]TC}"><field name="picture">#333333-#333333-#00ffff-#00ffff-#ffff00-#ffff00-#333333-#333333-#333333-#00ffff-#00ffff-#00ffff-#ffff00-#ffff00-#ffff00-#333333-#00ffff-#00ffff-#00ffff-#00ffff-#ffff00-#ffff00-#ffff00-#ffff00-#00ffff-#00ffff-#00ffff-#00ffff-#ffff00-#ffff00-#ffff00-#ffff00-#ffffff-#ffffff-#ffffff-#ffffff-#00ff00-#00ff00-#00ff00-#00ff00-#ffffff-#ffffff-#ffffff-#ffffff-#00ff00-#00ff00-#00ff00-#00ff00-#333333-#ffffff-#ffffff-#ffffff-#00ff00-#00ff00-#00ff00-#333333-#333333-#333333-#ffffff-#ffffff-#00ff00-#00ff00-#333333-#333333-#333333-#333333-#00ff00-#00ff00-#ffffff-#ffffff-#333333-#333333-#333333-#00ff00-#00ff00-#00ff00-#ffffff-#ffffff-#ffffff-#333333-#00ff00-#00ff00-#00ff00-#00ff00-#ffffff-#ffffff-#ffffff-#ffffff-#00ff00-#00ff00-#00ff00-#00ff00-#ffffff-#ffffff-#ffffff-#ffffff-#ff0000-#ff0000-#ff0000-#ff0000-#ffff00-#ffff00-#ffff00-#ffff00-#ff0000-#ff0000-#ff0000-#ff0000-#ffff00-#ffff00-#ffff00-#ffff00-#333333-#ff0000-#ff0000-#ff0000-#ffff00-#ffff00-#ffff00-#333333-#333333-#333333-#ff0000-#ff0000-#ffff00-#ffff00-#333333-#333333</field></shadow></value><next><block type="time_delay" id="0M.`a*jl5rWd|_khX{pe"><value name="DELAY_TIME_MILI"><block type="math_number" id="G1-IRVL2|xAba7,(y*8}"><field name="NUM">100</field></block></value><next><block type="hc_show_picture_n" id="mo!R21be(;IqME]I+eC]"><value name="picture"><shadow type="picture14" id="?VRG@[GjxatF_gAv5#,8"><field name="picture">#333333-#333333-#ffff00-#ffff00-#00ff00-#00ff00-#333333-#333333-#333333-#ffff00-#ffff00-#ffff00-#00ff00-#00ff00-#00ff00-#333333-#ffff00-#ffff00-#ffff00-#ffff00-#00ff00-#00ff00-#00ff00-#00ff00-#ffff00-#ffff00-#ffff00-#ffff00-#00ff00-#00ff00-#00ff00-#00ff00-#00ffff-#00ffff-#00ffff-#00ffff-#ffffff-#ffffff-#ffffff-#ffffff-#00ffff-#00ffff-#00ffff-#00ffff-#ffffff-#ffffff-#ffffff-#ffffff-#333333-#00ffff-#00ffff-#00ffff-#ffffff-#ffffff-#ffffff-#333333-#333333-#333333-#00ffff-#00ffff-#ffffff-#ffffff-#333333-#333333-#333333-#333333-#ffffff-#ffffff-#ffff00-#ffff00-#333333-#333333-#333333-#ffffff-#ffffff-#ffffff-#ffff00-#ffff00-#ffff00-#333333-#ffffff-#ffffff-#ffffff-#ffffff-#ffff00-#ffff00-#ffff00-#ffff00-#ffffff-#ffffff-#ffffff-#ffffff-#ffff00-#ffff00-#ffff00-#ffff00-#00ff00-#00ff00-#00ff00-#00ff00-#ff0000-#ff0000-#ff0000-#ff0000-#00ff00-#00ff00-#00ff00-#00ff00-#ff0000-#ff0000-#ff0000-#ff0000-#333333-#00ff00-#00ff00-#00ff00-#ff0000-#ff0000-#ff0000-#333333-#333333-#333333-#00ff00-#00ff00-#ff0000-#ff0000-#333333-#333333</field></shadow></value></block></next></block></next></block></next></block></next></block></next></block></next></block></next></block></next></block></next></block></next></block></next></block></next></block></next></block></next></block></next></block></next></block></statement></block><block type="hc_queen_setup" id="hc_queen_setup" deletable="false" x="-113" y="-8"></block><block type="hc_queen_loop" id="hc_queen_loop" deletable="false" x="-109" y="67"><statement name="LOOP_FUNC"><block type="procedures_callnoreturn" id="X2|XA0Y,1!]Lk^k5oF+."><mutation name="effect5"></mutation></block></statement></block></xml>